hypothesis_graphql/__init__.py
hypothesis_graphql/cache.py
hypothesis_graphql/nodes.py
hypothesis_graphql/py.typed
hypothesis_graphql/strategies.py
hypothesis_graphql/types.py
hypothesis_graphql/_strategies/__init__.py
hypothesis_graphql/_strategies/aliases.py
hypothesis_graphql/_strategies/ast.py
hypothesis_graphql/_strategies/containers.py
hypothesis_graphql/_strategies/factories.py
hypothesis_graphql/_strategies/primitives.py
hypothesis_graphql/_strategies/strategy.py
hypothesis_graphql/_strategies/validation.py
hypothesis_graphql-0.10.0.dist-info/METADATA
hypothesis_graphql-0.10.0.dist-info/WHEEL
hypothesis_graphql-0.10.0.dist-info/licenses/LICENSE
hypothesis_graphql-0.10.0.dist-info/RECORD
