Metadata-Version: 2.1
Name: hypothesis-graphql
Version: 0.10.0
Summary: Hypothesis strategies for GraphQL queries
Project-URL: Changelog, https://github.com/Stranger6667/hypothesis-graphql/blob/master/CHANGELOG.md
Project-URL: Bug Tracker, https://github.com/Stranger6667/hypothesis-graphql
Project-URL: Funding, https://github.com/sponsors/Stranger6667
Project-URL: Source Code, https://github.com/Stranger6667/hypothesis-graphql
Author-email: Dmitry Dygalo <dadygalo@gmail.com>
Maintainer-email: Dmitry Dygalo <dadygalo@gmail.com>
License-Expression: MIT
License-File: LICENSE
Keywords: graphql,hypothesis,testing
Classifier: Development Status :: 4 - Beta
Classifier: Environment :: Console
Classifier: Framework :: Hypothesis
Classifier: Intended Audience :: Developers
Classifier: License :: OSI Approved :: MIT License
Classifier: Operating System :: OS Independent
Classifier: Programming Language :: Python :: 3 :: Only
Classifier: Programming Language :: Python :: 3.7
Classifier: Programming Language :: Python :: 3.8
Classifier: Programming Language :: Python :: 3.9
Classifier: Programming Language :: Python :: 3.10
Classifier: Programming Language :: Python :: 3.11
Classifier: Programming Language :: Python :: Implementation :: CPython
Classifier: Topic :: Software Development :: Testing
Requires-Python: >=3.7
Requires-Dist: graphql-core<3.3.0,>=3.1.0
Requires-Dist: hypothesis<7.0,>=5.8.0
Provides-Extra: cov
Requires-Dist: coverage-enable-subprocess; extra == 'cov'
Requires-Dist: coverage[toml]>=7; extra == 'cov'
Provides-Extra: dev
Requires-Dist: hypothesis-graphql[cov,tests]; extra == 'dev'
Provides-Extra: tests
Requires-Dist: coverage>=7; extra == 'tests'
Requires-Dist: pytest-xdist<3.0,>=2.5; extra == 'tests'
Requires-Dist: pytest<8,>=6.2.0; extra == 'tests'
